operon_ai/__init__.py
operon_ai/cell.py
operon_ai/coordination/__init__.py
operon_ai/coordination/controller.py
operon_ai/coordination/morphogen.py
operon_ai/coordination/priority.py
operon_ai/coordination/system.py
operon_ai/coordination/types.py
operon_ai/coordination/watchdog.py
operon_ai/core/__init__.py
operon_ai/core/agent.py
operon_ai/core/types.py
operon_ai/core/wagent.py
operon_ai/core/wiring_runtime.py
operon_ai/healing/__init__.py
operon_ai/healing/autophagy_daemon.py
operon_ai/healing/chaperone_loop.py
operon_ai/healing/regenerative_swarm.py
operon_ai/health/__init__.py
operon_ai/health/epiplexity.py
operon_ai/memory/__init__.py
operon_ai/memory/episodic.py
operon_ai/organelles/__init__.py
operon_ai/organelles/chaperone.py
operon_ai/organelles/lysosome.py
operon_ai/organelles/membrane.py
operon_ai/organelles/mitochondria.py
operon_ai/organelles/nucleus.py
operon_ai/organelles/ribosome.py
operon_ai/providers/__init__.py
operon_ai/providers/anthropic_provider.py
operon_ai/providers/base.py
operon_ai/providers/gemini_provider.py
operon_ai/providers/mock.py
operon_ai/providers/openai_provider.py
operon_ai/quality/__init__.py
operon_ai/quality/components.py
operon_ai/quality/proteasome.py
operon_ai/quality/types.py
operon_ai/state/__init__.py
operon_ai/state/genome.py
operon_ai/state/histone.py
operon_ai/state/metabolism.py
operon_ai/state/telomere.py
operon_ai/surveillance/__init__.py
operon_ai/surveillance/display.py
operon_ai/surveillance/immune_system.py
operon_ai/surveillance/innate.py
operon_ai/surveillance/memory.py
operon_ai/surveillance/tcell.py
operon_ai/surveillance/thymus.py
operon_ai/surveillance/treg.py
operon_ai/surveillance/types.py
operon_ai/topology/__init__.py
operon_ai/topology/cascade.py
operon_ai/topology/loops.py
operon_ai/topology/oscillator.py
operon_ai/topology/quorum.py
operon_ai-0.11.0.dist-info/METADATA
operon_ai-0.11.0.dist-info/WHEEL
operon_ai-0.11.0.dist-info/licenses/LICENSE
operon_ai-0.11.0.dist-info/RECORD
