Metadata-Version: 2.4
Name: operon-ai
Version: 0.11.0
Summary: Biomimetic wiring diagrams for robust agentic systems.
Project-URL: Homepage, https://github.com/coredipper/operon
Author-email: Bogdan Banu <bogdan@banu.be>
License-Expression: MIT
License-File: LICENSE
Keywords: agents,biology,category-theory,llm,reliability
Classifier: Development Status :: 3 - Alpha
Classifier: Intended Audience :: Developers
Classifier: Topic :: Scientific/Engineering :: Artificial Intelligence
Requires-Python: >=3.11
Requires-Dist: pydantic>=2.0
Provides-Extra: dev
Requires-Dist: pytest>=7.0; extra == 'dev'
Provides-Extra: llm
Requires-Dist: anthropic>=0.18.0; extra == 'llm'
Requires-Dist: google-genai>=1.0.0; extra == 'llm'
Requires-Dist: openai>=1.0.0; extra == 'llm'
